qcatch/__init__.py
qcatch/api.py
qcatch/convert_to_html.py
qcatch/input_processing.py
qcatch/logger.py
qcatch/main.py
qcatch/plots_tables.py
qcatch/utils.py
qcatch/find_retained_cells/README.md
qcatch/find_retained_cells/__init__.py
qcatch/find_retained_cells/cell_calling.py
qcatch/find_retained_cells/constants.py
qcatch/find_retained_cells/feature_ref.py
qcatch/find_retained_cells/h5_constants.py
qcatch/find_retained_cells/matrix.py
qcatch/find_retained_cells/run_cell_calling.py
qcatch/find_retained_cells/sgt.py
qcatch/fry_tools/__init__.py
qcatch/fry_tools/loader.py
qcatch/templates/__init__.py
qcatch/templates/report_template.html
qcatch-0.2.8.dist-info/METADATA
qcatch-0.2.8.dist-info/WHEEL
qcatch-0.2.8.dist-info/entry_points.txt
qcatch-0.2.8.dist-info/licenses/LICENSE
qcatch-0.2.8.dist-info/RECORD
