Metadata-Version: 2.4
Name: qcatch
Version: 0.2.8
Summary: QCatch: Automated quality control of single-cell quantifications from `alevin-fry` and `simpleaf`.
Project-URL: Documentation, https://github.com/COMBINE-lab/QCatch#readme
Project-URL: Homepage, https://github.com/COMBINE-lab/QCatch
Project-URL: Source, https://github.com/COMBINE-lab/QCatch
Author: Yuan Gao, Dongze He, Rob Patro
License-File: LICENSE
Classifier: Programming Language :: Python :: 3 :: Only
Classifier: Programming Language :: Python :: 3.11
Classifier: Programming Language :: Python :: 3.12
Classifier: Programming Language :: Python :: 3.13
Requires-Python: >=3.11
Requires-Dist: anndata>=0.11.4
Requires-Dist: beautifulsoup4>=4.13.3
Requires-Dist: igraph<0.12,>=0.11
Requires-Dist: numpy<3,>=2.1.3
Requires-Dist: pandas<3,>=2.2.3
Requires-Dist: plotly>=6
Requires-Dist: requests>=2.32.4
Requires-Dist: scanpy<2,>=1.10.4
Requires-Dist: scipy<2,>=1.15.2
Requires-Dist: session-info2<0.2,>=0.1
Provides-Extra: dev
Requires-Dist: pre-commit; extra == 'dev'
Requires-Dist: twine>=4.0.2; extra == 'dev'
Provides-Extra: test
Requires-Dist: coverage; extra == 'test'
Requires-Dist: pytest; extra == 'test'
Requires-Dist: pytest-cov; extra == 'test'
Requires-Dist: setuptools; extra == 'test'
